[
  {
    "id": "CD_001",
    "name": "Shuttle Run Intervals",
    "status": "active",
    "conditioning_bucket": "aerobic_power",
    "energy_system": "aerobic",
    "work_rest_profile": "continuous",
    "cns_load": "low",
    "default_duration_sec": 60,
    "intensity": "med",
    "age_min": 10,
    "age_max": 99,
    "equipment": "Cones",
    "space": "20 yd lane",
    "step_by_step": "Run down and back continuously for duration",
    "coaching_cues": "Smooth pace, no sprinting",
    "video_url": null,
    "session_type": "conditioning",
    "inspired_by": "self",
    "coach_preference": 1
  },
  {
    "id": "CD_002",
    "name": "Hill Sprint Intervals",
    "status": "active",
    "conditioning_bucket": "repeat_sprint",
    "energy_system": "anaerobic_alactic",
    "work_rest_profile": "interval_long_rest",
    "cns_load": "high",
    "default_duration_sec": 30,
    "intensity": "high",
    "age_min": 12,
    "age_max": 99,
    "equipment": "Hill",
    "space": "20–30 yd hill",
    "step_by_step": "Sprint uphill hard, walk back down for recovery",
    "coaching_cues": "Drive knees, forward lean",
    "video_url": null,
    "session_type": "conditioning",
    "inspired_by": "self",
    "coach_preference": 1
  },
  {
    "id": "CD_003",
    "name": "Hill Sprint + Broad Jump Combo",
    "status": "active",
    "conditioning_bucket": "mixed_direction",
    "energy_system": "anaerobic_alactic",
    "work_rest_profile": "interval_long_rest",
    "cns_load": "high",
    "default_duration_sec": 45,
    "intensity": "high",
    "age_min": 14,
    "age_max": 99,
    "equipment": "Hill",
    "space": "20–30 yd hill",
    "step_by_step": "Sprint uphill, walk down, perform broad jumps up hill, walk down, repeat",
    "coaching_cues": "Land soft, quality jumps only",
    "video_url": null,
    "session_type": "conditioning",
    "inspired_by": "self",
    "coach_preference": 1
  },
  {
    "id": "CD_004",
    "name": "Treadmill Progressive Incline VO2 Run",
    "status": "active",
    "conditioning_bucket": "aerobic_power",
    "energy_system": "anaerobic_lactic",
    "work_rest_profile": "continuous",
    "cns_load": "high",
    "default_duration_sec": 600,
    "intensity": "med-high",
    "age_min": 14,
    "age_max": 99,
    "equipment": "Treadmill",
    "space": "Treadmill",
    "step_by_step": "2 min warm-up at low incline, then increase incline by 0.5 every 30s for 6 min, finish with 2 min cooldown",
    "coaching_cues": "Maintain posture as incline increases",
    "video_url": null,
    "session_type": "conditioning",
    "inspired_by": "self",
    "coach_preference": 1
  },
  {
    "id": "CD_005",
    "name": "Treadmill Progressive Speed VO2 Run",
    "status": "active",
    "conditioning_bucket": "aerobic_power",
    "energy_system": "anaerobic_lactic",
    "work_rest_profile": "continuous",
    "cns_load": "high",
    "default_duration_sec": 480,
    "intensity": "med-high",
    "age_min": 14,
    "age_max": 99,
    "equipment": "Treadmill",
    "space": "Treadmill",
    "step_by_step": "2 min warm-up at jog pace with 4–5 incline, increase speed by 0.5 each minute for 5 min, finish with 1 min incline walk",
    "coaching_cues": "Increase speed smoothly, no sprinting",
    "video_url": null,
    "session_type": "conditioning",
    "inspired_by": "self",
    "coach_preference": 1
  },
  {
    "id": "CD_006",
    "name": "Bike Mountain Climb VO2 Ladder",
    "status": "active",
    "conditioning_bucket": "aerobic_power",
    "energy_system": "anaerobic_lactic",
    "work_rest_profile": "interval_short_rest",
    "cns_load": "high",
    "default_duration_sec": 600,
    "intensity": "high",
    "age_min": 14,
    "age_max": 99,
    "equipment": "Stationary bike",
    "space": "Bike",
    "step_by_step": "Each minute perform sprint at high resistance for 20,40,60,80,100,120,100,80,60,40,20 pedal pushes, recover remaining time",
    "coaching_cues": "Stay seated, smooth powerful strokes",
    "video_url": null,
    "session_type": "conditioning",
    "inspired_by": "self",
    "coach_preference": 1
  },
  {
    "id": "CD_007",
    "name": "Bike Pyramid Power Intervals",
    "status": "active",
    "conditioning_bucket": "aerobic_power",
    "energy_system": "anaerobic_lactic",
    "work_rest_profile": "interval_short_rest",
    "cns_load": "high",
    "default_duration_sec": 480,
    "intensity": "med-high",
    "age_min": 14,
    "age_max": 99,
    "equipment": "Stationary bike",
    "space": "Bike",
    "step_by_step": "Each minute sprint for 30,45,60,75,90,75,60,45,30 pedal pushes, recover remaining time",
    "coaching_cues": "Consistent cadence, no bouncing",
    "video_url": null,
    "session_type": "conditioning",
    "inspired_by": "self",
    "coach_preference": 1
  },
  {
    "id": "CD_008",
    "name": "Bike Repeat Sprint VO2 Waves",
    "status": "active",
    "conditioning_bucket": "repeat_sprint",
    "energy_system": "anaerobic_lactic",
    "work_rest_profile": "interval_short_rest",
    "cns_load": "high",
    "default_duration_sec": 480,
    "intensity": "high",
    "age_min": 14,
    "age_max": 99,
    "equipment": "Stationary bike",
    "space": "Bike",
    "step_by_step": "Alternate minutes of 40 pedal pushes sprint and 60 pedal pushes sprint for total duration",
    "coaching_cues": "Power stays high on every effort",
    "video_url": null,
    "session_type": "conditioning",
    "inspired_by": "self",
    "coach_preference": 1
  },
  {
    "id": "CD_009",
    "name": "Continuous Stair Run",
    "status": "active",
    "conditioning_bucket": "aerobic_power",
    "energy_system": "aerobic",
    "work_rest_profile": "continuous",
    "cns_load": "moderate",
    "default_duration_sec": 60,
    "intensity": "med-high",
    "age_min": 12,
    "age_max": 99,
    "equipment": "Stairs",
    "space": "Stairwell",
    "step_by_step": "Run stairs continuously",
    "coaching_cues": "Drive through legs",
    "video_url": null,
    "session_type": "conditioning",
    "inspired_by": "self",
    "coach_preference": 1
  },
  {
    "id": "CD_010",
    "name": "Step-Up Intervals",
    "status": "active",
    "conditioning_bucket": "aerobic_power",
    "energy_system": "aerobic",
    "work_rest_profile": "continuous",
    "cns_load": "low",
    "default_duration_sec": 45,
    "intensity": "med",
    "age_min": 10,
    "age_max": 99,
    "equipment": "Box",
    "space": "1 box",
    "step_by_step": "Alternate step-ups continuously",
    "coaching_cues": "Full foot on box",
    "video_url": null,
    "session_type": "conditioning",
    "inspired_by": "self",
    "coach_preference": 1
  },
  {
    "id": "CD_011",
    "name": "Bike Long Climb VO2 Endurance",
    "status": "active",
    "conditioning_bucket": "aerobic_power",
    "energy_system": "anaerobic_lactic",
    "work_rest_profile": "interval_short_rest",
    "cns_load": "moderate",
    "default_duration_sec": 540,
    "intensity": "med-high",
    "age_min": 14,
    "age_max": 99,
    "equipment": "Stationary bike",
    "space": "Bike",
    "step_by_step": "Every minute perform 70 pedal pushes at moderate-high resistance for duration",
    "coaching_cues": "Don’t spike early, hold rhythm",
    "video_url": null,
    "session_type": "conditioning",
    "inspired_by": "self",
    "coach_preference": 1
  },
  {
    "id": "CD_012",
    "name": "Bike Descending VO2 Sprints",
    "status": "active",
    "conditioning_bucket": "repeat_sprint",
    "energy_system": "anaerobic_lactic",
    "work_rest_profile": "interval_short_rest",
    "cns_load": "high",
    "default_duration_sec": 480,
    "intensity": "high",
    "age_min": 14,
    "age_max": 99,
    "equipment": "Stationary bike",
    "space": "Bike",
    "step_by_step": "Each minute sprint for 100,90,80,70,60,50,40,30 pedal pushes, recover remaining time",
    "coaching_cues": "Stay powerful even as volume drops",
    "video_url": null,
    "session_type": "conditioning",
    "inspired_by": "self",
    "coach_preference": 1
  },
  {
    "id": "CD_013",
    "name": "Tempo Shuttle (1:1 Rest)",
    "status": "active",
    "conditioning_bucket": "tempo_base",
    "energy_system": "aerobic",
    "work_rest_profile": "interval_equal",
    "cns_load": "low",
    "default_duration_sec": 75,
    "intensity": "med",
    "age_min": 10,
    "age_max": 99,
    "equipment": "Cones",
    "space": "20 yd lane",
    "step_by_step": "Run shuttles, equal rest",
    "coaching_cues": "Heart rate controlled",
    "video_url": null,
    "session_type": "conditioning",
    "inspired_by": "self",
    "coach_preference": 1
  },
  {
    "id": "CD_014",
    "name": "Lateral Cone Touch Conditioning",
    "status": "active",
    "conditioning_bucket": "mixed_direction",
    "energy_system": "aerobic",
    "work_rest_profile": "continuous",
    "cns_load": "low",
    "default_duration_sec": 60,
    "intensity": "med",
    "age_min": 10,
    "age_max": 99,
    "equipment": "Cones",
    "space": "10x10 yd",
    "step_by_step": "Shuffle touching cones continuously",
    "coaching_cues": "Stay athletic",
    "video_url": null,
    "session_type": "conditioning",
    "inspired_by": "self",
    "coach_preference": 1
  },
  {
    "id": "CD_015",
    "name": "Continuous Squat Walk",
    "status": "active",
    "conditioning_bucket": "aerobic_power",
    "energy_system": "aerobic",
    "work_rest_profile": "continuous",
    "cns_load": "moderate",
    "default_duration_sec": 45,
    "intensity": "med-high",
    "age_min": 12,
    "age_max": 99,
    "equipment": null,
    "space": "10 yd lane",
    "step_by_step": "Squat walk forward and backward",
    "coaching_cues": "Burn legs, steady pace",
    "video_url": null,
    "session_type": "conditioning",
    "inspired_by": "self",
    "coach_preference": 1
  },
  {
    "id": "CD_016",
    "name": "Change-of-Pace VO2 Run",
    "status": "active",
    "conditioning_bucket": "aerobic_power",
    "energy_system": "anaerobic_lactic",
    "work_rest_profile": "interval_equal",
    "cns_load": "moderate",
    "default_duration_sec": 600,
    "intensity": "med-high",
    "age_min": 12,
    "age_max": 99,
    "equipment": null,
    "space": "30 yd lane",
    "step_by_step": "Alternate 30s hard run and 30s moderate run continuously for duration",
    "coaching_cues": "Never stop moving, control breathing",
    "video_url": null,
    "session_type": "conditioning",
    "inspired_by": "self",
    "coach_preference": 1
  },
  {
    "id": "CD_017",
    "name": "Curved Treadmill 1 Minute Sprint Interval",
    "status": "active",
    "conditioning_bucket": "repeat_sprint",
    "energy_system": "anaerobic_alactic",
    "work_rest_profile": "interval_long_rest",
    "cns_load": "high",
    "default_duration_sec": 30,
    "intensity": "high",
    "age_min": 14,
    "age_max": 99,
    "equipment": "Curved treadmill",
    "space": "Treadmill",
    "step_by_step": "5 hard sprints using prescribed work/rest options",
    "coaching_cues": "Increase sprint time gradually, cap at 30/30",
    "video_url": null,
    "session_type": "conditioning",
    "inspired_by": "self",
    "coach_preference": 1
  },
  {
    "id": "CD_033",
    "name": "Continuous Lateral Push VO2",
    "status": "active",
    "conditioning_bucket": "aerobic_power",
    "energy_system": "aerobic",
    "work_rest_profile": "continuous",
    "cns_load": "moderate",
    "default_duration_sec": 60,
    "intensity": "med-high",
    "age_min": 12,
    "age_max": 99,
    "equipment": null,
    "space": "10 yd lane",
    "step_by_step": "Continuous lateral push-offs side to side for duration",
    "coaching_cues": "Stay low, rhythmic breathing",
    "video_url": null,
    "session_type": "conditioning",
    "inspired_by": "self",
    "coach_preference": 1
  },
  {
    "id": "CD_019",
    "name": "Forward-Lateral Combo Conditioning",
    "status": "active",
    "conditioning_bucket": "mixed_direction",
    "energy_system": "aerobic",
    "work_rest_profile": "continuous",
    "cns_load": "moderate",
    "default_duration_sec": 60,
    "intensity": "med-high",
    "age_min": 12,
    "age_max": 99,
    "equipment": null,
    "space": "15 yd lane",
    "step_by_step": "Run forward then lateral shuffle",
    "coaching_cues": "Control breathing in recovery",
    "video_url": null,
    "session_type": "conditioning",
    "inspired_by": "self",
    "coach_preference": 1
  },
  {
    "id": "CD_020",
    "name": "Lunge-Run Combo Intervals",
    "status": "active",
    "conditioning_bucket": "aerobic_power",
    "energy_system": "aerobic",
    "work_rest_profile": "interval_equal",
    "cns_load": "moderate",
    "default_duration_sec": 60,
    "intensity": "med-high",
    "age_min": 12,
    "age_max": 99,
    "equipment": null,
    "space": "20 yd lane",
    "step_by_step": "Alternate 30s walking lunges and 30s light run",
    "coaching_cues": "Stay smooth on transitions",
    "video_url": null,
    "session_type": "conditioning",
    "inspired_by": "self",
    "coach_preference": 1
  }
]